deepdiver/__init__.py
deepdiver/content_processor.py
deepdiver/deepdive.py
deepdiver/deepdiver.yaml
deepdiver/notebooklm_automator.py
deepdiver/podcast_manager.py
deepdiver/session_tracker.py
deepdiver-0.1.0.dist-info/licenses/LICENSE
deepdiver-0.1.0.dist-info/METADATA
deepdiver-0.1.0.dist-info/WHEEL
deepdiver-0.1.0.dist-info/entry_points.txt
deepdiver-0.1.0.dist-info/top_level.txt
deepdiver-0.1.0.dist-info/RECORD
