Metadata-Version: 2.4
Name: deepdiver
Version: 0.1.0
Summary: NotebookLM Podcast Automation System - Automate podcast creation from documents
Home-page: https://github.com/gmusic/deepdiver
Author: gerico1007
Author-email: gerico1007 <gerico@jgwill.com>
Project-URL: Homepage, https://github.com/Gerico1007/deepdiver
Project-URL: Repository, https://github.com/Gerico1007/deepdiver
Project-URL: Issues, https://github.com/Gerico1007/deepdiver/issues
Keywords: notebooklm,podcast,automation,audio,browser-automation,playwright
Classifier: Development Status :: 3 - Alpha
Classifier: Intended Audience :: Developers
Classifier: License :: OSI Approved :: MIT License
Classifier: Operating System :: OS Independent
Classifier: Programming Language :: Python :: 3
Classifier: Programming Language :: Python :: 3.8
Classifier: Programming Language :: Python :: 3.9
Classifier: Programming Language :: Python :: 3.10
Classifier: Programming Language :: Python :: 3.11
Classifier: Programming Language :: Python :: 3.12
Classifier: Topic :: Multimedia :: Sound/Audio
Classifier: Topic :: Office/Business
Classifier: Topic :: Software Development :: Libraries :: Python Modules
Requires-Python: >=3.8
License-File: LICENSE
Requires-Dist: playwright>=1.40.0
Requires-Dist: pyyaml>=6.0
Requires-Dist: requests>=2.31.0
Requires-Dist: beautifulsoup4>=4.12.0
Requires-Dist: pyperclip>=1.8.2
Requires-Dist: click>=8.1.0
Requires-Dist: rich>=13.0.0
Provides-Extra: dev
Requires-Dist: pytest>=7.4.0; extra == "dev"
Requires-Dist: pytest-asyncio>=0.21.0; extra == "dev"
Requires-Dist: black>=23.0.0; extra == "dev"
Requires-Dist: flake8>=6.0.0; extra == "dev"
Requires-Dist: mypy>=1.5.0; extra == "dev"
Dynamic: author
Dynamic: home-page
Dynamic: license-file
Dynamic: requires-python
